MANIFEST.in
VERSION
setup.py
mc_server_manager/__init__.py
mc_server_manager/mc_server_manager.py
mc_server_manager.egg-info/PKG-INFO
mc_server_manager.egg-info/SOURCES.txt
mc_server_manager.egg-info/dependency_links.txt
mc_server_manager.egg-info/entry_points.txt
mc_server_manager.egg-info/not-zip-safe
mc_server_manager.egg-info/requires.txt
mc_server_manager.egg-info/top_level.txt