Metadata-Version: 1.0
Name: mc-server-manager
Version: 0.3.2
Summary: Manages Servers on AWS
Home-page: https://github.com/bwilliam0/mc-server-manager
Author: bwilliam0
Author-email: dev@mycodeiscompiling.com
License: Apache License 2.0
Platform: UNKNOWN
